ceasylog/Logger.py
ceasylog/LoggerConfiger.py
ceasylog/LoggerLevel.py
ceasylog/LoggerNetworkConfiger.py
ceasylog/LoggerStatic.py
ceasylog/__init__.py
casseroles-1.2.7.dist-info/LICENSE
casseroles-1.2.7.dist-info/METADATA
casseroles-1.2.7.dist-info/WHEEL
casseroles-1.2.7.dist-info/top_level.txt
casseroles-1.2.7.dist-info/RECORD
