Metadata-Version: 2.1
Name: casseroles
Version: 1.2.7
Summary: A great log util from CandyStar
Author: CandyStar@HuangXudong
License: Apache License 2.0
Keywords: ceasylog
Platform: any
License-File: LICENSE
Requires-Dist: colorama
Requires-Dist: requests
